.gitignore
LICENSE
README.md
logo.png
requirements.txt
setup.cfg
setup.py
maleo/__init__.py
maleo/documentation.md
maleo.egg-info/PKG-INFO
maleo.egg-info/SOURCES.txt
maleo.egg-info/dependency_links.txt
maleo.egg-info/requires.txt
maleo.egg-info/top_level.txt
maleo/cleansing/Emoticon_Dict.p
maleo/cleansing/__init__.py
maleo/cleansing/_cleansing.py
maleo/pos_tag/__init__.py
maleo/pos_tag/_pos.py
maleo/preprocessing/Emoji_Dict.p
maleo/preprocessing/__init__.py
maleo/preprocessing/_preprocessing.py
maleo/preprocessing/slang_dict.json
maleo/scanner/__init__.py
maleo/scanner/_scanner.py
maleo/stopword_remover/ArrayDictionary.py
maleo/stopword_remover/Remover.py
maleo/stopword_remover/RemoverFactory.py
maleo/stopword_remover/__init__.py
maleo/stopword_remover/indo_stopwords.txt
maleo/wizard/__init__.py
maleo/wizard/_wizard.py