Metadata-Version: 2.1
Name: maleo
Version: 0.0.7.0
Summary: Wrapper library for text cleansing, preprocessing in NLP
Home-page: https://github.com/jakartaresearch/maleo
Author: Ruben Stefanus
Author-email: researchjair@gmail.com
License: MIT
Download-URL: https://github.com/jakartaresearch/maleo/archive/v0.0.7.0.tar.gz
Keywords: nlp,text-processing,machine-learning
Platform: UNKNOWN
Classifier: Development Status :: 3 - Alpha
Classifier: Intended Audience :: Developers
Classifier: Topic :: Software Development :: Build Tools
Classifier: Topic :: Scientific/Engineering :: Artificial Intelligence
Classifier: Topic :: Text Processing
Classifier: License :: OSI Approved :: MIT License
Classifier: Programming Language :: Python :: 3
Classifier: Programming Language :: Python :: 3.6
Classifier: Programming Language :: Python :: 3.7
Classifier: Programming Language :: Python :: 3.8
